dglabv3/__init__.py
dglabv3/dglab.py
dglabv3/dtype.py
dglabv3/event.py
dglabv3/waves.py
dglabv3/wsmessage.py
dglabv3-0.2.4.dist-info/LICENSE
dglabv3-0.2.4.dist-info/METADATA
dglabv3-0.2.4.dist-info/WHEEL
dglabv3-0.2.4.dist-info/top_level.txt
dglabv3-0.2.4.dist-info/RECORD
