Metadata-Version: 2.2
Name: dglabv3
Version: 0.2.4
Summary: a dglab v3 lib
Author-email: phillychi3 <phillychi3@gmail.com>
License:                     GNU GENERAL PUBLIC LICENSE
Project-URL: Repository, https://github.com/phillychi3/dglab-v3-python.git
Keywords: dglab
Classifier: Programming Language :: Python :: 3
Requires-Python: >=3.8
License-File: LICENSE
Requires-Dist: websockets
Requires-Dist: qrcode
